yival/__init__.py
yival/__main__.py
yival/auto_prompt/__init__.py
yival/auto_prompt/default_task.py
yival/auto_prompt/main.py
yival/cli/__init__.py
yival/cli/bot.py
yival/cli/demo.py
yival/cli/gen.py
yival/cli/init.py
yival/cli/run.py
yival/cli/task.py
yival/cli/utils.py
yival/cli/validate.py
yival/common/__init__.py
yival/common/auto_cofig_utils.py
yival/common/doc_similarity_utils.py
yival/common/huggingface/__init__.py
yival/common/huggingface/generator.py
yival/common/huggingface/helpers.py
yival/common/huggingface/hf.py
yival/common/model_utils.py
yival/common/utils.py
yival/configs/__init__.py
yival/configs/config_utils.py
yival/data/__init__.py
yival/data/base_reader.py
yival/data/csv_reader.py
yival/data/dataset/truthful_qa.csv
yival/data/huggingface_dataset_reader.py
yival/data_generators/__init__.py
yival/data_generators/base_data_generator.py
yival/data_generators/document_data_generator.py
yival/data_generators/openai_prompt_data_generator.py
yival/dataset/__init__.py
yival/dataset/data_utils.py
yival/demo/__init__.py
yival/demo/configs/auto_prompts_config.yml
yival/demo/configs/basic_interactive_config.yml
yival/demo/configs/qa_expected_results_config.yml
yival/demo/data/yival_expected_results.csv
yival/demo/headline_generation.py
yival/demo/qa.py
yival/demo/translation.py
yival/enhancers/__init__.py
yival/enhancers/base_combination_enhancer.py
yival/enhancers/openai_prompt_based_combination_enhancer.py
yival/enhancers/optimize_by_prompt_enhancer.py
yival/enhancers/pe2_enhancer.py
yival/enhancers/utils.py
yival/evaluators/__init__.py
yival/evaluators/alpaca_eval_evaluator.py
yival/evaluators/base_evaluator.py
yival/evaluators/bertscore_evaluator.py
yival/evaluators/openai_elo_evaluator.py
yival/evaluators/openai_prompt_based_evaluator.py
yival/evaluators/python_validation_evaluator.py
yival/evaluators/rouge_evaluator.py
yival/evaluators/string_expected_result_evaluator.py
yival/evaluators/utils.py
yival/experiment/__init__.py
yival-0.1.0a10.dist-info/LICENSE
yival-0.1.0a10.dist-info/METADATA
yival-0.1.0a10.dist-info/WHEEL
yival-0.1.0a10.dist-info/entry_points.txt
yival-0.1.0a10.dist-info/RECORD
