Metadata-Version: 2.1
Name: yival
Version: 0.1.0a10
Summary: YiVal is an open-source project designed to revolutionize the way developers and researchers evaluate and refine AI models.
License: Apachev2
Author: Tao Feng
Author-email: taofeng.nju@gmail.com
Requires-Python: >=3.10,<3.13
Classifier: License :: Other/Proprietary License
Classifier: Programming Language :: Python :: 3
Classifier: Programming Language :: Python :: 3.10
Classifier: Programming Language :: Python :: 3.11
Provides-Extra: trainers
Requires-Dist: aiohttp-socks (>=0.8.0,<0.9.0)
Requires-Dist: alpaca-eval (>=0.3.1,<0.4.0)
Requires-Dist: bert-score (>=0.3.13,<0.4.0)
Requires-Dist: bitsandbytes (>=0.41.1,<0.42.0) ; extra == "trainers"
Requires-Dist: dash (>=2.11.1,<3.0.0)
Requires-Dist: dash-bootstrap-components (>=1.4.2,<2.0.0)
Requires-Dist: dash-dangerously-set-inner-html (>=0.0.2,<0.0.3)
Requires-Dist: faiss-cpu (>=1.7.4,<2.0.0)
Requires-Dist: fuzzywuzzy (>=0.18.0,<0.19.0)
Requires-Dist: google-api-python-client (==2.84.0)
Requires-Dist: google-auth-httplib2 (==0.1.1)
Requires-Dist: google-auth-oauthlib (==1.0.0)
Requires-Dist: hydra-core (>=1.3.2,<2.0.0)
Requires-Dist: inquirer (>=3.1.3,<4.0.0)
Requires-Dist: langchain (>=0.0.275,<0.0.276)
Requires-Dist: litellm (==0.1.607)
Requires-Dist: numpy (>=1.25.2,<2.0.0)
Requires-Dist: omegaconf (>=2.3.0,<3.0.0)
Requires-Dist: openai (==0.27.10)
Requires-Dist: pandas (>=2.0.3,<3.0.0)
Requires-Dist: pandas-stubs (>=2.1.1.230928,<3.0.0.0)
Requires-Dist: pdf2image (==1.16.3)
Requires-Dist: peft (>=0.5.0,<0.6.0) ; extra == "trainers"
Requires-Dist: pillow (==9.4.0)
Requires-Dist: psutil (>=5.9.5,<6.0.0)
Requires-Dist: pydantic (>=2.1.1,<3.0.0)
Requires-Dist: pydoc-markdown (>=4.8.2,<5.0.0)
Requires-Dist: pyngrok (>=6.0.0,<7.0.0)
Requires-Dist: pytesseract (==0.3.10)
Requires-Dist: python-levenshtein (>=0.21.1,<0.22.0)
Requires-Dist: replicate (>=0.12.0,<0.13.0)
Requires-Dist: rich (>=13.4.2,<14.0.0)
Requires-Dist: rouge (>=1.0.1,<2.0.0)
Requires-Dist: scipy (>=1.11.3,<2.0.0) ; extra == "trainers"
Requires-Dist: streamlit (>=1.27.2,<2.0.0)
Requires-Dist: tabulate (==0.9.0)
Requires-Dist: tenacity (>=8.2.3,<9.0.0)
Requires-Dist: tiktoken (>=0.4.0,<0.5.0)
Requires-Dist: torch (>=2.0.0,!=2.0.1,!=2.1.0)
Requires-Dist: tqdm (>=4.65.0,<5.0.0)
Requires-Dist: transformers (>=4.33.0,<5.0.0)
Requires-Dist: trl (>=0.7.1,<0.8.0) ; extra == "trainers"
Requires-Dist: types-pillow (>=10.0.0.2,<11.0.0.0)
Requires-Dist: types-pyyaml (>=6.0.12.11,<7.0.0.0)
Requires-Dist: types-requests (>=2.31.0.2,<3.0.0.0)
Requires-Dist: types-tqdm (>=4.65.0.2,<5.0.0.0)
Requires-Dist: unstructured (==0.6.6)
